pyrice/__init__.py
pyrice/build_dictionary.py
pyrice/database_description.xml
pyrice/main.py
pyrice/multi_query.py
pyrice/utils.py
pyrice/support/.DS_Store
pyrice/support/gwas_atlas.json
pyrice/support/id_dict.pkl
pyrice/support/iric_dict.pkl
pyrice/support/loc_dict.pkl
pyrice/support/oryzabase.pkl
pyrice/support/rapdb.pkl
pyrice/support/download/download_history.log
pyrice-0.2.11.dist-info/LICENSE.txt
pyrice-0.2.11.dist-info/METADATA
pyrice-0.2.11.dist-info/WHEEL
pyrice-0.2.11.dist-info/top_level.txt
pyrice-0.2.11.dist-info/RECORD
