Metadata-Version: 2.1
Name: pyrice
Version: 0.2.11
Summary: PyRice: a Python package for functional analysis of rice genes
Home-page: https://github.com/SouthGreenPlatform/PyRice
Author: Pierre Larmande, Quan Do
Author-email: pierre.larmande@ird.fr, dohongquan1612@gmail.com
License: MIT
Classifier: Programming Language :: Python :: 3
Classifier: Programming Language :: Python :: 3.8
Classifier: License :: OSI Approved :: MIT License
Classifier: Operating System :: OS Independent
License-File: LICENSE.txt
Requires-Dist: selenium
